<annotation>
	<folder>Diseased_Leaves.copy</folder>
	<filename>images-w1789.jpeg</filename>
	<path>J:\software\Work.diseased\Copy\Diseased_Leaves.copy\images-w1789.jpeg</path>
	<source>
		<database>Unknown</database>
	</source>
	<size>
		<width>218</width>
		<height>232</height>
		<depth>3</depth>
	</size>
	<segmented>0</segmented>
	<object>
		<name>Diseased_Leaves</name>
		<pose>Unspecified</pose>
		<truncated>0</truncated>
		<difficult>0</difficult>
		<bndbox>
			<xmin>100</xmin>
			<ymin>24</ymin>
			<xmax>138</xmax>
			<ymax>101</ymax>
		</bndbox>
	</object>
	<object>
		<name>Diseased_Leaves</name>
		<pose>Unspecified</pose>
		<truncated>0</truncated>
		<difficult>0</difficult>
		<bndbox>
			<xmin>78</xmin>
			<ymin>105</ymin>
			<xmax>138</xmax>
			<ymax>133</ymax>
		</bndbox>
	</object>
	<object>
		<name>Diseased_Leaves</name>
		<pose>Unspecified</pose>
		<truncated>0</truncated>
		<difficult>0</difficult>
		<bndbox>
			<xmin>139</xmin>
			<ymin>143</ymin>
			<xmax>204</xmax>
			<ymax>183</ymax>
		</bndbox>
	</object>
	<object>
		<name>Diseased_Leaves</name>
		<pose>Unspecified</pose>
		<truncated>1</truncated>
		<difficult>0</difficult>
		<bndbox>
			<xmin>1</xmin>
			<ymin>125</ymin>
			<xmax>80</xmax>
			<ymax>170</ymax>
		</bndbox>
	</object>
	<object>
		<name>Diseased_Leaves</name>
		<pose>Unspecified</pose>
		<truncated>0</truncated>
		<difficult>0</difficult>
		<bndbox>
			<xmin>51</xmin>
			<ymin>179</ymin>
			<xmax>87</xmax>
			<ymax>205</ymax>
		</bndbox>
	</object>
</annotation>
