<annotation>
	<folder>Diseased_Leaves.copy</folder>
	<filename>images-w1771.jpeg</filename>
	<path>J:\software\Work.diseased\Copy\Diseased_Leaves.copy\images-w1771.jpeg</path>
	<source>
		<database>Unknown</database>
	</source>
	<size>
		<width>183</width>
		<height>275</height>
		<depth>3</depth>
	</size>
	<segmented>0</segmented>
	<object>
		<name>Diseased_Leaves</name>
		<pose>Unspecified</pose>
		<truncated>0</truncated>
		<difficult>0</difficult>
		<bndbox>
			<xmin>78</xmin>
			<ymin>124</ymin>
			<xmax>86</xmax>
			<ymax>130</ymax>
		</bndbox>
	</object>
	<object>
		<name>Diseased_Leaves</name>
		<pose>Unspecified</pose>
		<truncated>0</truncated>
		<difficult>0</difficult>
		<bndbox>
			<xmin>76</xmin>
			<ymin>143</ymin>
			<xmax>93</xmax>
			<ymax>158</ymax>
		</bndbox>
	</object>
	<object>
		<name>Diseased_Leaves</name>
		<pose>Unspecified</pose>
		<truncated>0</truncated>
		<difficult>0</difficult>
		<bndbox>
			<xmin>144</xmin>
			<ymin>153</ymin>
			<xmax>155</xmax>
			<ymax>167</ymax>
		</bndbox>
	</object>
	<object>
		<name>Diseased_Leaves</name>
		<pose>Unspecified</pose>
		<truncated>0</truncated>
		<difficult>0</difficult>
		<bndbox>
			<xmin>78</xmin>
			<ymin>37</ymin>
			<xmax>97</xmax>
			<ymax>77</ymax>
		</bndbox>
	</object>
	<object>
		<name>Diseased_Leaves</name>
		<pose>Unspecified</pose>
		<truncated>0</truncated>
		<difficult>0</difficult>
		<bndbox>
			<xmin>154</xmin>
			<ymin>61</ymin>
			<xmax>175</xmax>
			<ymax>84</ymax>
		</bndbox>
	</object>
	<object>
		<name>Diseased_Leaves</name>
		<pose>Unspecified</pose>
		<truncated>0</truncated>
		<difficult>0</difficult>
		<bndbox>
			<xmin>92</xmin>
			<ymin>170</ymin>
			<xmax>101</xmax>
			<ymax>196</ymax>
		</bndbox>
	</object>
</annotation>
